pyrawsocket-0.0.1.dist-info/METADATA
pyrawsocket-0.0.1.dist-info/RECORD
pyrawsocket-0.0.1.dist-info/WHEEL
pyrawsocket-0.0.1.dist-info/top_level.txt
rawsocket/__init__.py
rawsocket/afpacket.py
rawsocket/ioport.py
rawsocket/iothread.py
rawsocket/util.py
