Metadata-Version: 2.1
Name: pyrawsocket
Version: 0.0.1
Summary: Raw Socket package
Home-page: https://github.com/cboling/pyRawSocket
Author: Chip Boling
Author-email: chip@bcsw.net
License: UNKNOWN
Platform: UNKNOWN
Classifier: Development Status :: 3 - Alpha
Classifier: Intended Audience :: Developers
Classifier: Topic :: Software Development :: Libraries
Classifier: License :: OSI Approved :: Apache Software License
Classifier: Programming Language :: Python :: 3.6
Classifier: Programming Language :: Python :: 3.7
Requires-Dist: virtualenv (>=20.0.25)
Requires-Dist: packaging (==20.4)
Requires-Dist: scapy (==2.4.3)
Requires-Dist: pcapy (==0.11.4)
